setup.cfg
setup.py
cabot_alert_email/__init__.py
cabot_alert_email/models.py
cabot_alert_email.egg-info/PKG-INFO
cabot_alert_email.egg-info/SOURCES.txt
cabot_alert_email.egg-info/dependency_links.txt
cabot_alert_email.egg-info/top_level.txt
cabot_alert_email/migrations/0001_initial.py
cabot_alert_email/migrations/__init__.py
cabot_alert_email/tests/__init__.py
cabot_alert_email/tests/test_email.py