Metadata-Version: 1.1
Name: cabot-alert-email
Version: 1.4.3
Summary: An email alert plugin for Cabot by Arachnys
Home-page: http://cabotapp.com
Author: Arachnys
Author-email: info@arachnys.org
License: UNKNOWN
Download-URL: https://github.com/cabotapp/cabot-alert-email/archive/1.4.3.zip
Platform: UNKNOWN
